psychtoolbox/GetSecs.cp36-win_amd64.pyd
psychtoolbox/IOPort.cp36-win_amd64.pyd
psychtoolbox/PsychHID.cp36-win_amd64.pyd
psychtoolbox/PsychPortAudio.cp36-win_amd64.pyd
psychtoolbox/WaitSecs.cp36-win_amd64.pyd
psychtoolbox/__init__.py
psychtoolbox/_abi3_wheel.py
psychtoolbox/_version.py
psychtoolbox/audio.py
psychtoolbox/hid.py
psychtoolbox/libusb-1.0.dll
psychtoolbox/portaudio_x64.dll
psychtoolbox/demos/__init__.py
psychtoolbox/demos/hidtest_oldschool.py
psychtoolbox/demos/hidtest_pythonic.py
psychtoolbox/demos/ppatest_oldschool.py
psychtoolbox/demos/ppatest_pythonic.py
psychtoolbox-3.0.19.0.dist-info/METADATA
psychtoolbox-3.0.19.0.dist-info/WHEEL
psychtoolbox-3.0.19.0.dist-info/top_level.txt
psychtoolbox-3.0.19.0.dist-info/RECORD
